[
  {
    "strategy": "A_OnDemand",
    "batch_size": 2,
    "run_id": 0,
    "inference_latency_ms": 4562.943999999975,
    "memory_usage_mb": 28.0,
    "cache_hit_rate": 0.0003255208333333333,
    "expert_transfer_time_ms": 0.0,
    "gpu_utilization": 0.85,
    "prefetch_accuracy": 0.0,
    "total_experts_loaded": 6142,
    "cache_misses": 6142,
    "timestamp": 1753125858.0424037
  },
  {
    "strategy": "A_OnDemand",
    "batch_size": 2,
    "run_id": 1,
    "inference_latency_ms": 4562.943999999975,
    "memory_usage_mb": 28.0,
    "cache_hit_rate": 0.0003255208333333333,
    "expert_transfer_time_ms": 0.0,
    "gpu_utilization": 0.85,
    "prefetch_accuracy": 0.0,
    "total_experts_loaded": 6142,
    "cache_misses": 6142,
    "timestamp": 1753125858.0465686
  },
  {
    "strategy": "A_OnDemand",
    "batch_size": 2,
    "run_id": 2,
    "inference_latency_ms": 4562.943999999975,
    "memory_usage_mb": 28.0,
    "cache_hit_rate": 0.0003255208333333333,
    "expert_transfer_time_ms": 0.0,
    "gpu_utilization": 0.85,
    "prefetch_accuracy": 0.0,
    "total_experts_loaded": 6142,
    "cache_misses": 6142,
    "timestamp": 1753125858.0507166
  },
  {
    "strategy": "A_OnDemand",
    "batch_size": 2,
    "run_id": 3,
    "inference_latency_ms": 4562.943999999975,
    "memory_usage_mb": 28.0,
    "cache_hit_rate": 0.0003255208333333333,
    "expert_transfer_time_ms": 0.0,
    "gpu_utilization": 0.85,
    "prefetch_accuracy": 0.0,
    "total_experts_loaded": 6142,
    "cache_misses": 6142,
    "timestamp": 1753125858.0548232
  },
  {
    "strategy": "A_OnDemand",
    "batch_size": 2,
    "run_id": 4,
    "inference_latency_ms": 4562.943999999975,
    "memory_usage_mb": 28.0,
    "cache_hit_rate": 0.0003255208333333333,
    "expert_transfer_time_ms": 0.0,
    "gpu_utilization": 0.85,
    "prefetch_accuracy": 0.0,
    "total_experts_loaded": 6142,
    "cache_misses": 6142,
    "timestamp": 1753125858.058924
  },
  {
    "strategy": "A_OnDemand",
    "batch_size": 2,
    "run_id": 5,
    "inference_latency_ms": 4562.943999999975,
    "memory_usage_mb": 28.0,
    "cache_hit_rate": 0.0003255208333333333,
    "expert_transfer_time_ms": 0.0,
    "gpu_utilization": 0.85,
    "prefetch_accuracy": 0.0,
    "total_experts_loaded": 6142,
    "cache_misses": 6142,
    "timestamp": 1753125858.0630486
  },
  {
    "strategy": "A_OnDemand",
    "batch_size": 2,
    "run_id": 6,
    "inference_latency_ms": 4562.943999999975,
    "memory_usage_mb": 28.0,
    "cache_hit_rate": 0.0003255208333333333,
    "expert_transfer_time_ms": 0.0,
    "gpu_utilization": 0.85,
    "prefetch_accuracy": 0.0,
    "total_experts_loaded": 6142,
    "cache_misses": 6142,
    "timestamp": 1753125858.0671046
  },
  {
    "strategy": "A_OnDemand",
    "batch_size": 2,
    "run_id": 7,
    "inference_latency_ms": 4562.943999999975,
    "memory_usage_mb": 28.0,
    "cache_hit_rate": 0.0003255208333333333,
    "expert_transfer_time_ms": 0.0,
    "gpu_utilization": 0.85,
    "prefetch_accuracy": 0.0,
    "total_experts_loaded": 6142,
    "cache_misses": 6142,
    "timestamp": 1753125858.0711782
  },
  {
    "strategy": "A_OnDemand",
    "batch_size": 2,
    "run_id": 8,
    "inference_latency_ms": 4562.943999999975,
    "memory_usage_mb": 28.0,
    "cache_hit_rate": 0.0003255208333333333,
    "expert_transfer_time_ms": 0.0,
    "gpu_utilization": 0.85,
    "prefetch_accuracy": 0.0,
    "total_experts_loaded": 6142,
    "cache_misses": 6142,
    "timestamp": 1753125858.0752625
  },
  {
    "strategy": "A_OnDemand",
    "batch_size": 2,
    "run_id": 9,
    "inference_latency_ms": 4562.943999999975,
    "memory_usage_mb": 28.0,
    "cache_hit_rate": 0.0003255208333333333,
    "expert_transfer_time_ms": 0.0,
    "gpu_utilization": 0.85,
    "prefetch_accuracy": 0.0,
    "total_experts_loaded": 6142,
    "cache_misses": 6142,
    "timestamp": 1753125858.0792859
  }
]